Workbook

Sheet Dashboard
A1: Meghan Lahti for Mayor 2026 — Campaign Budget
A2: Live tracker — every donation in, every dollar out, what's left to spend.
A4: KEY CAMPAIGN INFO | D4: FUNDS AT A GLANCE
A5: Election Day | B5: 46312 | C5: Verify exact date with Elections BC | D5: Total Raised | E5: Total Committed | F5: Remaining
A6: Days Until Election | B6: =$B$5-TODAY() -> 170 | D6: =Fundraising!E2 -> 700 | E6: =Expenses!H2 -> 0 | F6: =D6-E6 -> 700
A7: Campaign Account Holder | B7: Anthony Sandler (financial agent) | C7: Confirm with Meghan
A8: BC Max Donation / Individual | B8: 1429.7 | C8: Per BC Municipal Elections Finance Rules
A9: Eligible Donors | B9: BC residents only | C9: No corporate or union donations
A12: SPENDING BY CATEGORY
A13: Category | B13: Budgeted | C13: Committed | D13: Paid | E13: Remaining | F13: % of Budget
A14: Lawn Signs | B14: 5000 | C14: =SUMIFS(Expenses!$F:$F,Expenses!$B:$B,$A14,Expenses!$G:$G,"Committed")+SUMIFS(Expenses!$F:$F,Expenses!$B:$B,$A14,Expenses!$G:$G,"Planned")+SUMIFS(Expenses!$F:$F,Expenses!$B:$B,$A14,Expenses!$G:$G,"Paid") -> 0 | D14: =SUMIFS(Expenses!$F:$F,Expenses!$B:$B,$A14,Expenses!$G:$G,"Paid") -> 0 | E14: =B14-C14 -> 5000 | F14: =IFERROR(C14/B14,0) -> 0
A15: Door-knocking & Literature | B15: 2000 | C15: =SUMIFS(Expenses!$F:$F,Expenses!$B:$B,$A15,Expenses!$G:$G,"Committed")+SUMIFS(Expenses!$F:$F,Expenses!$B:$B,$A15,Expenses!$G:$G,"Planned")+SUMIFS(Expenses!$F:$F,Expenses!$B:$B,$A15,Expenses!$G:$G,"Paid") -> 0 | D15: =SUMIFS(Expenses!$F:$F,Expenses!$B:$B,$A15,Expenses!$G:$G,"Paid") -> 0 | E15: =B15-C15 -> 2000 | F15: =IFERROR(C15/B15,0) -> 0
A16: Direct Mail | B16: 6000 | C16: =SUMIFS(Expenses!$F:$F,Expenses!$B:$B,$A16,Expenses!$G:$G,"Committed")+SUMIFS(Expenses!$F:$F,Expenses!$B:$B,$A16,Expenses!$G:$G,"Planned")+SUMIFS(Expenses!$F:$F,Expenses!$B:$B,$A16,Expenses!$G:$G,"Paid") -> 0 | D16: =SUMIFS(Expenses!$F:$F,Expenses!$B:$B,$A16,Expenses!$G:$G,"Paid") -> 0 | E16: =B16-C16 -> 6000 | F16: =IFERROR(C16/B16,0) -> 0
A17: Digital Ads (Facebook, Google) | B17: 3000 | C17: =SUMIFS(Expenses!$F:$F,Expenses!$B:$B,$A17,Expenses!$G:$G,"Committed")+SUMIFS(Expenses!$F:$F,Expenses!$B:$B,$A17,Expenses!$G:$G,"Planned")+SUMIFS(Expenses!$F:$F,Expenses!$B:$B,$A17,Expenses!$G:$G,"Paid") -> 0 | D17: =SUMIFS(Expenses!$F:$F,Expenses!$B:$B,$A17,Expenses!$G:$G,"Paid") -> 0 | E17: =B17-C17 -> 3000 | F17: =IFERROR(C17/B17,0) -> 0
A18: Print Ads (Tri-City News, etc.) | B18: 2000 | C18: =SUMIFS(Expenses!$F:$F,Expenses!$B:$B,$A18,Expenses!$G:$G,"Committed")+SUMIFS(Expenses!$F:$F,Expenses!$B:$B,$A18,Expenses!$G:$G,"Planned")+SUMIFS(Expenses!$F:$F,Expenses!$B:$B,$A18,Expenses!$G:$G,"Paid") -> 0 | D18: =SUMIFS(Expenses!$F:$F,Expenses!$B:$B,$A18,Expenses!$G:$G,"Paid") -> 0 | E18: =B18-C18 -> 2000 | F18: =IFERROR(C18/B18,0) -> 0
A19: Photography & Video | B19: 1500 | C19: =SUMIFS(Expenses!$F:$F,Expenses!$B:$B,$A19,Expenses!$G:$G,"Committed")+SUMIFS(Expenses!$F:$F,Expenses!$B:$B,$A19,Expenses!$G:$G,"Planned")+SUMIFS(Expenses!$F:$F,Expenses!$B:$B,$A19,Expenses!$G:$G,"Paid") -> 0 | D19: =SUMIFS(Expenses!$F:$F,Expenses!$B:$B,$A19,Expenses!$G:$G,"Paid") -> 0 | E19: =B19-C19 -> 1500 | F19: =IFERROR(C19/B19,0) -> 0
A20: Website & Tech | B20: 1000 | C20: =SUMIFS(Expenses!$F:$F,Expenses!$B:$B,$A20,Expenses!$G:$G,"Committed")+SUMIFS(Expenses!$F:$F,Expenses!$B:$B,$A20,Expenses!$G:$G,"Planned")+SUMIFS(Expenses!$F:$F,Expenses!$B:$B,$A20,Expenses!$G:$G,"Paid") -> 0 | D20: =SUMIFS(Expenses!$F:$F,Expenses!$B:$B,$A20,Expenses!$G:$G,"Paid") -> 0 | E20: =B20-C20 -> 1000 | F20: =IFERROR(C20/B20,0) -> 0
A21: Events (kickoff, town halls) | B21: 2500 | C21: =SUMIFS(Expenses!$F:$F,Expenses!$B:$B,$A21,Expenses!$G:$G,"Committed")+SUMIFS(Expenses!$F:$F,Expenses!$B:$B,$A21,Expenses!$G:$G,"Planned")+SUMIFS(Expenses!$F:$F,Expenses!$B:$B,$A21,Expenses!$G:$G,"Paid") -> 0 | D21: =SUMIFS(Expenses!$F:$F,Expenses!$B:$B,$A21,Expenses!$G:$G,"Paid") -> 0 | E21: =B21-C21 -> 2500 | F21: =IFERROR(C21/B21,0) -> 0
A22: Volunteer Costs (food, swag) | B22: 1000 | C22: =SUMIFS(Expenses!$F:$F,Expenses!$B:$B,$A22,Expenses!$G:$G,"Committed")+SUMIFS(Expenses!$F:$F,Expenses!$B:$B,$A22,Expenses!$G:$G,"Planned")+SUMIFS(Expenses!$F:$F,Expenses!$B:$B,$A22,Expenses!$G:$G,"Paid") -> 0 | D22: =SUMIFS(Expenses!$F:$F,Expenses!$B:$B,$A22,Expenses!$G:$G,"Paid") -> 0 | E22: =B22-C22 -> 1000 | F22: =IFERROR(C22/B22,0) -> 0
A23: Branded Merchandise | B23: 1500 | C23: =SUMIFS(Expenses!$F:$F,Expenses!$B:$B,$A23,Expenses!$G:$G,"Committed")+SUMIFS(Expenses!$F:$F,Expenses!$B:$B,$A23,Expenses!$G:$G,"Planned")+SUMIFS(Expenses!$F:$F,Expenses!$B:$B,$A23,Expenses!$G:$G,"Paid") -> 0 | D23: =SUMIFS(Expenses!$F:$F,Expenses!$B:$B,$A23,Expenses!$G:$G,"Paid") -> 0 | E23: =B23-C23 -> 1500 | F23: =IFERROR(C23/B23,0) -> 0
A24: Polling / Research | B24: 0 | C24: =SUMIFS(Expenses!$F:$F,Expenses!$B:$B,$A24,Expenses!$G:$G,"Committed")+SUMIFS(Expenses!$F:$F,Expenses!$B:$B,$A24,Expenses!$G:$G,"Planned")+SUMIFS(Expenses!$F:$F,Expenses!$B:$B,$A24,Expenses!$G:$G,"Paid") -> 0 | D24: =SUMIFS(Expenses!$F:$F,Expenses!$B:$B,$A24,Expenses!$G:$G,"Paid") -> 0 | E24: =B24-C24 -> 0 | F24: =IFERROR(C24/B24,0) -> 0
A25: Contingency (~10%) | B25: 2500 | C25: =SUMIFS(Expenses!$F:$F,Expenses!$B:$B,$A25,Expenses!$G:$G,"Committed")+SUMIFS(Expenses!$F:$F,Expenses!$B:$B,$A25,Expenses!$G:$G,"Planned")+SUMIFS(Expenses!$F:$F,Expenses!$B:$B,$A25,Expenses!$G:$G,"Paid") -> 0 | D25: =SUMIFS(Expenses!$F:$F,Expenses!$B:$B,$A25,Expenses!$G:$G,"Paid") -> 0 | E25: =B25-C25 -> 2500 | F25: =IFERROR(C25/B25,0) -> 0
A26: TOTAL | B26: =SUM(B14:B25) -> 28000 | C26: =SUM(C14:C25) -> 0 | D26: =SUM(D14:D25) -> 0 | E26: =SUM(E14:E25) -> 28000 | F26: =IFERROR(C26/B26,0) -> 0
A28: HOW TO USE
A29: 1. Edit YELLOW cells. They are inputs you control. Black cells are formulas — don't touch.
A30: 2. Log every donation on the FUNDRAISING tab. Total Raised on this dashboard updates automatically.
A31: 3. Log every expense on the EXPENSES tab. Use the 'Status' column: Planned / Committed / Paid.
A32: 4. Update vendor rates on the VENDOR RATES tab as quotes come in.
A33: 5. Use the SCENARIO CALCULATOR tab to test 'what if we mail all 14,000 households' before committing.
A34: 6. Watch the Remaining number in the top-right. If it goes negative, slow down.

Sheet Fundraising
A1: Fundraising Tracker
D2: TOTAL RAISED | E2: =SUMIF(F:F,"Received",D:D) -> 700 | F2: PLEDGED | G2: =SUMIF(F:F,"Pledged",D:D) -> 0
A4: Date | B4: Donor Name | C4: Email / Phone | D4: Amount | E4: Type | F4: Status | G4: Notes | I4: BC COMPLIANCE FLAG
A5: 46128 | B5: [Sample] Jane Smith | C5: jane@example.com | D5: 200 | E5: Individual | F5: Received | G5: Fundraiser attendee | I5: Max per donor: | J5: =Dashboard!B8 -> 1429.7
A6: 46128 | B6: [Sample] John Doe | C6: john@example.com | D6: 500 | E6: Individual | F6: Received | G6: Fundraiser attendee | I6: Donors over limit: | J6: =IFERROR(SUMPRODUCT((D5:D500>0)*(SUMIF(B5:B500,B5:B500,D5:D500)>J5)/COUNTIF(B5:B500,B5:B500&"")),0) -> 0
I7: (Watch this — must stay zero)

Sheet Vendor Rates
A1: Vendor Rate Card
A2: Pre-loaded with industry estimates. Replace with real quotes as you get them. Yellow = your inputs.
A4: Item | B4: Vendor | C4: Unit | D4: Unit Rate | E4: Notes | F4: Quote Date
A5: Lawn sign (yard, 18x24) | B5: TBD | C5: per sign | D5: 10 | E5: Estimate $8-15. Quantity discounts at 200+
A6: Lawn sign stakes / wickets | B6: TBD | C6: per stake | D6: 1.5 | E6: Often bundled with signs
A7: Large signs (4x8) | B7: TBD | C7: per sign | D7: 120 | E7: Estimate $80-150 each
A8: Door hangers / palm cards | B8: TBD | C8: per piece | D8: 0.4 | E8: Estimate $0.30-0.50; depends on stock & qty
A9: Direct mail postcard (Canada Post) | B9: Canada Post Personalized Mail | C9: per piece | D9: 0.5 | E9: Estimate $0.40-0.60 incl. printing & postage
A10: Lawn-sign installation | B10: Volunteer | C10: per sign | D10: 0 | E10: Volunteers cover this — $0
A11: Facebook / Meta ads | B11: Meta | C11: per $1 spend | D11: 1 | E11: Variable CPM/CPC; budget-driven
A12: Google ads | B12: Google | C12: per $1 spend | D12: 1 | E12: Variable; budget-driven
A13: Tri-City News print ad (1/4 page) | B13: Tri-City News | C13: per insertion | D13: 600 | E13: Estimate — confirm rate card
A14: Photography (event) | B14: TBD | C14: per session | D14: 400 | E14: 2-3 hr coverage
A15: Video (Butters Studio) | B15: Butters Studio | C15: per project | D15: 0 | E15: Already commissioned — fill in actual cost
A16: Website hosting + domain | B16: Netlify + Registrar | C16: per year | D16: 200 | E16: Small static-site hosting
... A22: Polling (if any) | B22: TBD | C22: per project | D22: 5000 | E22: Typically out-of-budget for municipal

Sheet Expenses
A1: Expense Tracker
G2: TOTAL COMMITTED + PAID | H2: =SUMIF(G:G,"Committed",F:F)+SUMIF(G:G,"Planned",F:F)+SUMIF(G:G,"Paid",F:F) -> 0
A4: Date | B4: Category | C4: Description | D4: Vendor | E4: Quantity | F4: Total Cost | G4: Status | H4: Notes
A5: 46140 | B5: Photography & Video | C5: Butters Studio — announcement video | D5: Butters Studio | E5: 1 | F5: 0 | G5: Planned | H5: Confirm final invoice
A6: 46128 | B6: Events (kickoff, town halls) | C6: Fundraiser venue + light catering | D6: TBD | E6: 1 | F6: 0 | G6: Paid | H6: Confirm exact spend with Meghan

Sheet Scenario Calculator
A1: What-If Scenario Calculator
A2: Plug in numbers to see what something would cost BEFORE you commit. Yellow = your inputs.
A4: REFERENCE DATA
A5: Port Moody — total households (approx.) | B5: 14000 | C5: Verify with latest census
A6: Coronation Park / Balmoral Place units | B6: 88 | C6: Per Leah Prentice
A7: Moody Centre area households (approx.) | B7: 2500 | C7: Estimate — verify
A8: Inlet Centre area households (approx.) | B8: 3500 | C8: Estimate — verify
A9: Heritage Mountain households (approx.) | B9: 1800 | C9: Estimate — verify
A12: SCENARIO A — DIRECT MAIL DROP
A13: Households to mail to | B13: 14000
A14: Cost per piece (from Vendor Rates) | B14: ='Vendor Rates'!D9 -> 0.5
A15: Total cost | B15: =B13*B14 -> 7000
A16: % of $30K total budget | B16: =B15/30000 -> 0.23333333
A19: SCENARIO B — LAWN SIGN PROGRAM
A20: Number of lawn signs | B20: 300
A21: Cost per sign | B21: ='Vendor Rates'!D5 -> 10
A22: Number of stakes | B22: =B20 -> 300
A23: Cost per stake | B23: ='Vendor Rates'!D6 -> 1.5
A24: Number of large 4x8 signs | B24: 4
A25: Cost per large sign | B25: ='Vendor Rates'!D7 -> 120
A26: Total cost | B26: =B20*B21+B22*B23+B24*B25 -> 3930
A28: SCENARIO C — DOOR-HANGER DROP
A29: Households to canvass | B29: 5000
A30: Cost per door hanger | B30: ='Vendor Rates'!D8 -> 0.4
A31: Total cost | B31: =B29*B30 -> 2000
A32: Volunteers needed (~50 doors / hr / volunteer) | B32: =B29/50 -> 100
A33: Volunteer hours total | B33: =B29/50 -> 100
A35: SCENARIO D — DIGITAL AD SPEND
A36: Total ad budget ($) | B36: 2000
A37: Estimated cost per click ($) | B37: 0.85
A38: Estimated clicks | B38: =B36/B37 -> 2352.9412
A39: Estimated cost per 1000 impressions ($) | B39: 8.5
A40: Estimated impressions | B40: =B36/B39*1000 -> 235294.12
A41: Reach as % of PM (rough) | B41: =B40/B5 -> 16.806723
